larsnico/__init__.py
larsnico/main.py
larsnico-1.3.dist-info/LICENSE
larsnico-1.3.dist-info/METADATA
larsnico-1.3.dist-info/WHEEL
larsnico-1.3.dist-info/entry_points.txt
larsnico-1.3.dist-info/top_level.txt
larsnico-1.3.dist-info/RECORD
