Metadata-Version: 2.1
Name: larsnico
Version: 1.3
Summary: UNKNOWN
Home-page: UNKNOWN
Author: nicriv
License: UNKNOWN
Platform: UNKNOWN
License-File: LICENSE
Requires-Dist: click
